LICENSE.txt
README.md
setup.cfg
setup.py
freesyntax/__init__.py
freesyntax/factory.py
freesyntax/grammar.py
freesyntax/structs.py
freesyntax.egg-info/PKG-INFO
freesyntax.egg-info/SOURCES.txt
freesyntax.egg-info/dependency_links.txt
freesyntax.egg-info/top_level.txt
freesyntax/lib2to3/__init__.py
freesyntax/lib2to3/__main__.py
freesyntax/lib2to3/btm_matcher.py
freesyntax/lib2to3/btm_utils.py
freesyntax/lib2to3/fixer_base.py
freesyntax/lib2to3/fixer_util.py
freesyntax/lib2to3/patcomp.py
freesyntax/lib2to3/pygram.py
freesyntax/lib2to3/pytree.py
freesyntax/lib2to3/refactor.py
freesyntax/lib2to3/pgen2/__init__.py
freesyntax/lib2to3/pgen2/conv.py
freesyntax/lib2to3/pgen2/driver.py
freesyntax/lib2to3/pgen2/grammar.py
freesyntax/lib2to3/pgen2/literals.py
freesyntax/lib2to3/pgen2/parse.py
freesyntax/lib2to3/pgen2/pgen.py
freesyntax/lib2to3/pgen2/token.py
freesyntax/lib2to3/pgen2/tokenize.py