Metadata-Version: 2.1
Name: freesyntax
Version: 0.0.1
Summary: Syntactically Free Python
Home-page: https://github.com/isidentical/freesyntax
Author: isidentical
License: UNKNOWN
Platform: UNKNOWN
Requires-Python: >=3.9
